{
  "id": "archive_aporee-57603-65939",
  "filename": "aporee-57603-65939_Haldonoverpasstopoftelegraphhill.wav",
  "title": "Haldon Chalets, Exeter EX6 7XW, UK - Haldon road across A380 Telegraph Hill- Devon Wildland",
  "channel": "talk_to_me",
  "source": "archive_org",
  "source_url": "https://archive.org/details/aporee_57603_65939",
  "source_id": "aporee_57603_65939",
  "license": "PD",
  "license_attribution": "kate.morley",
  "duration_sec": 0.0,
  "machine_type": "unknown",
  "machine_specifics": null,
  "mood_tags": [],
  "recorded_or_scraped": "scraped",
  "scraped_at": "2026-06-11T18:44:44.778544Z",
  "loudness_lufs": null,
  "sample_rate": null,
  "bitrate_kbps": null
}