{
  "id": "bbc_07063150",
  "filename": "07063150.mp3",
  "title": "Volkswagon Golf GL - keys, start up, belt up, city drive.",
  "channel": "in_your_ear",
  "source": "bbc",
  "source_url": "https://sound-effects.bbcrewind.co.uk/search?q=07063150",
  "source_id": "07063150",
  "license": "BBC-personal-use",
  "license_attribution": "BBC Sound Effects",
  "duration_sec": 178.66585,
  "machine_type": "unknown",
  "machine_specifics": null,
  "mood_tags": [],
  "recorded_or_scraped": "scraped",
  "scraped_at": "2026-06-11T18:47:51.467913Z",
  "loudness_lufs": -16.93,
  "sample_rate": 44100,
  "bitrate_kbps": 128
}